datalad_neuroimaging/__init__.py
datalad_neuroimaging/_version.py
datalad_neuroimaging/bids2scidata.py
datalad_neuroimaging/conftest.py
datalad_neuroimaging/version.py
datalad_neuroimaging/extractors/__init__.py
datalad_neuroimaging/extractors/bids.py
datalad_neuroimaging/extractors/bids_dataset.py
datalad_neuroimaging/extractors/dicom.py
datalad_neuroimaging/extractors/nidm.py
datalad_neuroimaging/extractors/nifti1.py
datalad_neuroimaging/extractors/tests/__init__.py
datalad_neuroimaging/extractors/tests/test_bids.py
datalad_neuroimaging/extractors/tests/test_bids_dataset.py
datalad_neuroimaging/extractors/tests/test_dicom.py
datalad_neuroimaging/extractors/tests/test_nidm.py
datalad_neuroimaging/extractors/tests/test_nifti1.py
datalad_neuroimaging/resources/isatab/scidata_bids_investigator.txt
datalad_neuroimaging/resources/procedures/cfg_bids.py
datalad_neuroimaging/tests/__init__.py
datalad_neuroimaging/tests/test_aggregation.py
datalad_neuroimaging/tests/test_bids2scidata.py
datalad_neuroimaging/tests/test_dicomconv.py
datalad_neuroimaging/tests/test_procedure.py
datalad_neuroimaging/tests/test_register.py
datalad_neuroimaging/tests/test_search.py
datalad_neuroimaging/tests/utils.py
datalad_neuroimaging/tests/data/files/dicom.dcm
datalad_neuroimaging/tests/data/files/nifti1.nii.gz
datalad_neuroimaging-0.3.7.dist-info/licenses/LICENSE
datalad_neuroimaging-0.3.7.dist-info/METADATA
datalad_neuroimaging-0.3.7.dist-info/WHEEL
datalad_neuroimaging-0.3.7.dist-info/entry_points.txt
datalad_neuroimaging-0.3.7.dist-info/top_level.txt
datalad_neuroimaging-0.3.7.dist-info/RECORD
