Metadata-Version: 2.4
Name: datalad_neuroimaging
Version: 0.3.7
Summary: DataLad extension package for neuro/medical imaging
Home-page: https://github.com/datalad/datalad-neuroimaging
Author: The DataLad Team and Contributors
Author-email: team@datalad.org
License: MIT
Classifier: Programming Language :: Python
Classifier: License :: OSI Approved :: BSD License
Classifier: Programming Language :: Python :: 3
Requires-Python: >=3.9
License-File: LICENSE
Requires-Dist: datalad>=0.16.7
Requires-Dist: datalad-deprecated>=0.2.7
Requires-Dist: pydicom>=2.0.0
Requires-Dist: pybids>=0.15.1
Requires-Dist: nibabel
Requires-Dist: pandas
Requires-Dist: datalad-metalad>=0.4.5
Provides-Extra: devel
Requires-Dist: pytest; extra == "devel"
Requires-Dist: pytest-cov; extra == "devel"
Requires-Dist: pypandoc; extra == "devel"
Requires-Dist: datalad>=0.17.0; extra == "devel"
Requires-Dist: sphinx>=1.6.2; extra == "devel"
Requires-Dist: sphinx-rtd-theme; extra == "devel"
Requires-Dist: heudiconv; extra == "devel"
Provides-Extra: devel-docs
Requires-Dist: pypandoc; extra == "devel-docs"
Requires-Dist: sphinx>=1.6.2; extra == "devel-docs"
Requires-Dist: sphinx-rtd-theme; extra == "devel-docs"
Provides-Extra: devel-downstream
Requires-Dist: heudiconv; extra == "devel-downstream"
Dynamic: license-file
